<?xml version="1.0" encoding="UTF-8"?>
<database>
    <element label="Technical Round 1" max_length="40" name="x_192471_placement_technical_round_1" type="collection">
        <element label="Company Name" max_length="32" name="u_company_name" reference="x_192471_placement_company_information" type="reference"/>
        <element label="Important Topics" max_length="2048" name="u_important_topics" type="string"/>
        <element label="Reason to take this round" max_length="2048" name="u_reason_to_take_this_round" type="string"/>
        <element label="Round Name" max_length="32" name="u_round_name" reference="x_192471_placement_interview_rounds" type="reference"/>
        <element label="Time Duration (Minute)" max_length="40" name="u_time_duration" type="integer"/>
        <index name="index">
            <element name="u_company_name"/>
        </index>
        <index name="index2">
            <element name="u_round_name"/>
        </index>
    </element>
</database>
